{
  "schemaVersion": 1,
  "id": "mini-rocket",
  "name": "Mini Rocket",
  "description": "A small 7-step rocket. Great starter build.",
  "pieceCount": 18,
  "steps": [
    {
      "stepNumber": 1,
      "description": "Lay the launch pad base",
      "pieces": [
        {"id": "s1p1", "type": "brick-2x4", "color": "#9e9e9e", "gridX": 0, "gridZ": 0, "layer": 0, "rotation": 0},
        {"id": "s1p2", "type": "brick-2x4", "color": "#9e9e9e", "gridX": 0, "gridZ": 4, "layer": 0, "rotation": 0}
      ]
    },
    {
      "stepNumber": 2,
      "description": "Add the fuel tank base",
      "pieces": [
        {"id": "s2p1", "type": "brick-2x4", "color": "#e3000b", "gridX": 0, "gridZ": 0, "layer": 1, "rotation": 0},
        {"id": "s2p2", "type": "brick-2x4", "color": "#e3000b", "gridX": 0, "gridZ": 4, "layer": 1, "rotation": 0}
      ]
    },
    {
      "stepNumber": 3,
      "description": "Continue the fuel tank",
      "pieces": [
        {"id": "s3p1", "type": "brick-2x4", "color": "#e3000b", "gridX": 0, "gridZ": 0, "layer": 2, "rotation": 0},
        {"id": "s3p2", "type": "brick-2x4", "color": "#e3000b", "gridX": 0, "gridZ": 4, "layer": 2, "rotation": 0}
      ]
    },
    {
      "stepNumber": 4,
      "description": "Add white accent stripe",
      "pieces": [
        {"id": "s4p1", "type": "brick-2x4", "color": "#ffffff", "gridX": 0, "gridZ": 0, "layer": 3, "rotation": 0},
        {"id": "s4p2", "type": "brick-2x4", "color": "#ffffff", "gridX": 0, "gridZ": 4, "layer": 3, "rotation": 0}
      ]
    },
    {
      "stepNumber": 5,
      "description": "Narrow the body with 2x2 bricks",
      "pieces": [
        {"id": "s5p1", "type": "brick-2x2", "color": "#e3000b", "gridX": 0, "gridZ": 1, "layer": 4, "rotation": 0},
        {"id": "s5p2", "type": "brick-2x2", "color": "#e3000b", "gridX": 0, "gridZ": 3, "layer": 4, "rotation": 0}
      ]
    },
    {
      "stepNumber": 6,
      "description": "Add the nose cone plates",
      "pieces": [
        {"id": "s6p1", "type": "plate-2x2", "color": "#e3000b", "gridX": 0, "gridZ": 2, "layer": 15, "rotation": 0},
        {"id": "s6p2", "type": "plate-2x2", "color": "#e3000b", "gridX": 0, "gridZ": 2, "layer": 16, "rotation": 0},
        {"id": "s6p3", "type": "plate-2x2", "color": "#ffffff", "gridX": 0, "gridZ": 2, "layer": 17, "rotation": 0}
      ]
    },
    {
      "stepNumber": 7,
      "description": "Cap the rocket tip with slopes",
      "pieces": [
        {"id": "s7p1", "type": "slope-2x1", "color": "#e3000b", "gridX": -1, "gridZ": 2, "layer": 6, "rotation": 0},
        {"id": "s7p2", "type": "slope-2x1", "color": "#e3000b", "gridX": 1, "gridZ": 2, "layer": 6, "rotation": 180},
        {"id": "s7p3", "type": "slope-2x1", "color": "#e3000b", "gridX": 0, "gridZ": 1, "layer": 6, "rotation": 90},
        {"id": "s7p4", "type": "slope-2x1", "color": "#e3000b", "gridX": 0, "gridZ": 3, "layer": 6, "rotation": 270},
        {"id": "s7p5", "type": "slope-2x1", "color": "#ffffff", "gridX": 0, "gridZ": 2, "layer": 7, "rotation": 0}
      ]
    }
  ]
}
